gitpulse/DynamicHTMLReportGenerator.py
gitpulse/GitDiff.py
gitpulse/HTMLReportGenerator.py
gitpulse/__init__.py
gitpulse/gitpulse_cli.py
gitpulse-1.2.dist-info/METADATA
gitpulse-1.2.dist-info/WHEEL
gitpulse-1.2.dist-info/entry_points.txt
gitpulse-1.2.dist-info/top_level.txt
gitpulse-1.2.dist-info/RECORD
