Metadata-Version: 2.1
Name: gitpulse
Version: 1.2
Requires-Dist: gitpython
Requires-Dist: jinja2
Requires-Dist: python-dateutil
